codefreaker/__init__.py
codefreaker/annotations.py
codefreaker/checker.py
codefreaker/clone.py
codefreaker/config.py
codefreaker/console.py
codefreaker/create.py
codefreaker/edit.py
codefreaker/grading/__init__.py
codefreaker/grading/judge/__init__.py
codefreaker/grading/judge/cacher.py
codefreaker/grading/judge/digester.py
codefreaker/grading/judge/sandbox.py
codefreaker/grading/judge/sandboxes/__init__.py
codefreaker/grading/judge/sandboxes/stupid_sandbox.py
codefreaker/grading/judge/storage.py
codefreaker/grading/judge/test.py
codefreaker/grading/steps.py
codefreaker/hydration.py
codefreaker/main.py
codefreaker/metadata.py
codefreaker/providers/__init__.py
codefreaker/providers/codeforces.py
codefreaker/providers/provider.py
codefreaker/schema.py
codefreaker/submit.py
codefreaker/submitors/__init__.py
codefreaker/submitors/codeforces.py
codefreaker/submitors/submitor.py
codefreaker/test.py
codefreaker/testcase.py
codefreaker/testcase_rendering.py
codefreaker/utils.py
codefreaker-0.1.3.dist-info/LICENSE
codefreaker-0.1.3.dist-info/METADATA
codefreaker-0.1.3.dist-info/WHEEL
codefreaker-0.1.3.dist-info/entry_points.txt
codefreaker-0.1.3.dist-info/RECORD
