Metadata-Version: 2.1
Name: codefreaker
Version: 0.1.3
Summary: 
Author: Roberto Sales
Requires-Python: >=3.10,<4.0
Classifier: Programming Language :: Python :: 3
Classifier: Programming Language :: Python :: 3.10
Classifier: Programming Language :: Python :: 3.11
Classifier: Programming Language :: Python :: 3.12
Requires-Dist: fastapi (>=0.111.0,<0.112.0)
Requires-Dist: filelock (>=3.14.0,<4.0.0)
Requires-Dist: gevent (>=24.2.1,<25.0.0)
Requires-Dist: jinja2 (>=3.1.4,<4.0.0)
Requires-Dist: mechanize (>=0.4.10,<0.5.0)
Requires-Dist: pydantic (>=2.7.3,<3.0.0)
Requires-Dist: rich (>=13.7.1,<14.0.0)
Requires-Dist: typer[all] (>=0.12.3,<0.13.0)
